[
  {
    "type": "string-start",
    "value": "\"",
    "offset": 0
  },
  {
    "type": "string-value",
    "value": "a",
    "offset": 1
  },
  {
    "type": "template-start",
    "value": "{",
    "offset": 2
  },
  {
    "type": "string-start",
    "value": "\"",
    "offset": 3
  },
  {
    "type": "string-value",
    "value": "b",
    "offset": 4
  },
  {
    "type": "template-start",
    "value": "{",
    "offset": 5
  },
  {
    "type": "string-start",
    "value": "\"",
    "offset": 6
  },
  {
    "type": "string-value",
    "value": "c",
    "offset": 7
  },
  {
    "type": "template-start",
    "value": "{",
    "offset": 8
  },
  {
    "type": "string-start",
    "value": "\"",
    "offset": 9
  },
  {
    "type": "string-value",
    "value": "d",
    "offset": 10
  },
  {
    "type": "string-end",
    "value": "\"",
    "offset": 11
  },
  {
    "type": "template-end",
    "value": "}",
    "offset": 12
  },
  {
    "type": "string-value",
    "value": "e",
    "offset": 13
  },
  {
    "type": "string-end",
    "value": "\"",
    "offset": 14
  },
  {
    "type": "template-end",
    "value": "}",
    "offset": 15
  },
  {
    "type": "string-value",
    "value": "f",
    "offset": 16
  },
  {
    "type": "string-end",
    "value": "\"",
    "offset": 17
  },
  {
    "type": "template-end",
    "value": "}",
    "offset": 18
  },
  {
    "type": "string-value",
    "value": "g",
    "offset": 19
  },
  {
    "type": "string-end",
    "value": "\"",
    "offset": 20
  }
]
